<map name="LM430DWBE_0"><area shape="rect" coords="875,88,1131,280" href="#273675-0" alt="273675-0: ASA A LM430D" title="273675-0: ASA A LM430D" /><area shape="rect" coords="1101,141,1116,180" href="#266459-3" alt="266459-3: TORNILLO M5X25 PC5001C" title="266459-3: TORNILLO M5X25 PC5001C" /><area shape="rect" coords="1163,220,1233,275" href="#453250-0" alt="453250-0: PALANCA BLOQUEO LM430D" title="453250-0: PALANCA BLOQUEO LM430D" /><area shape="rect" coords="1168,292,1227,337" href="#453251-8" alt="453251-8: SOPORTE PALANCA BLOQUEO LM430D" title="453251-8: SOPORTE PALANCA BLOQUEO LM430D" /><area shape="rect" coords="1149,325,1175,344" href="#233173-6" alt="233173-6: MUELLE COMPRESION UC4020A" title="233173-6: MUELLE COMPRESION UC4020A" /><area shape="rect" coords="1352,221,1763,586" href="#141300-0" alt="141300-0: TAPA TRASERA LM430D" title="141300-0: TAPA TRASERA LM430D" /><area shape="rect" coords="1755,766,1769,783" href="#961018-5" alt="961018-5: GRUPILLA E-5*" title="961018-5: GRUPILLA E-5*" /><area shape="rect" coords="1505,623,1751,770" href="#256871-5" alt="256871-5: BULON TAPA TRASERA LM430D" title="256871-5: BULON TAPA TRASERA LM430D" /><area shape="rect" coords="1403,574,1481,619" href="#233597-6" alt="233597-6: MUELLE TAPA TRASERA LM430D" title="233597-6: MUELLE TAPA TRASERA LM430D" /><area shape="rect" coords="1391,555,1405,572" href="#961018-5" alt="961018-5: GRUPILLA E-5*" title="961018-5: GRUPILLA E-5*" /><area shape="rect" coords="1196,898,1208,926" href="#266326-2" alt="266326-2: TORNILLO M4X18" title="266326-2: TORNILLO M4X18" /><area shape="rect" coords="823,383,835,411" href="#266326-2" alt="266326-2: TORNILLO M4X18" title="266326-2: TORNILLO M4X18" /><area shape="rect" coords="538,327,1383,1024" href="#453235-6" alt="453235-6: CARCASA MOTOR LM430D" title="453235-6: CARCASA MOTOR LM430D" /><area shape="rect" coords="528,493,619,631" href="#896597-3" alt="896597-3: LM430D NAME PLATE" title="896597-3: LM430D NAME PLATE" /><area shape="rect" coords="120,77,566,488" href="#141305-0" alt="141305-0: TAPA BATERIA LM430D" title="141305-0: TAPA BATERIA LM430D" /><area shape="rect" coords="488,716,500,744" href="#266326-2" alt="266326-2: TORNILLO M4X18" title="266326-2: TORNILLO M4X18" /><area shape="rect" coords="359,775,526,948" href="#187254-7" alt="187254-7: TERMINAL BATERIA LM430D" title="187254-7: TERMINAL BATERIA LM430D" /><area shape="rect" coords="346,798,432,879" href="#643849-1" alt="643849-1: TERMINAL BBC231U" title="643849-1: TERMINAL BBC231U" /><area shape="rect" coords="238,707,410,885" href="#187254-7" alt="187254-7: TERMINAL BATERIA LM430D" title="187254-7: TERMINAL BATERIA LM430D" /><area shape="rect" coords="324,1028,501,1158" href="#890383-4" alt="890383-4: MAKITA LOGO LABEL" title="890383-4: MAKITA LOGO LABEL" /><area shape="rect" coords="553,1112,701,1249" href="#453258-4" alt="453258-4: TAPA CARCASA MOTOR LM430D" title="453258-4: TAPA CARCASA MOTOR LM430D" /><area shape="rect" coords="664,1256,676,1284" href="#266326-2" alt="266326-2: TORNILLO M4X18" title="266326-2: TORNILLO M4X18" /><area shape="rect" coords="759,1155,780,1204" href="#266774-5" alt="266774-5: TORNILLO 6X30 LM430D" title="266774-5: TORNILLO 6X30 LM430D" /><area shape="rect" coords="778,1022,1043,1289" href="#629933-6" alt="629933-6: MOTOR LM430D" title="629933-6: MOTOR LM430D" /><area shape="rect" coords="1105,1044,1181,1202" href="#620084-8" alt="620084-8: CONTROLADOR LM430D" title="620084-8: CONTROLADOR LM430D" /><area shape="rect" coords="1054,1213,1066,1241" href="#266326-2" alt="266326-2: TORNILLO M4X18" title="266326-2: TORNILLO M4X18" /><area shape="rect" coords="1027,1259,1066,1282" href="#687123-7" alt="687123-7: PRESILLA P/MT601" title="687123-7: PRESILLA P/MT601" /><area shape="rect" coords="774,1305,829,1411" href="#643890-4" alt="643890-4: LLAVE LM430D" title="643890-4: LLAVE LM430D" /><area shape="rect" coords="743,1407,755,1436" href="#266326-2" alt="266326-2: TORNILLO M4X18" title="266326-2: TORNILLO M4X18" /><area shape="rect" coords="771,1420,866,1499" href="#638946-6" alt="638946-6: UNIDAD LED LM430D" title="638946-6: UNIDAD LED LM430D" /><area shape="rect" coords="619,1505,661,1538" href="#688165-4" alt="688165-4: FILTRO DE LINEA BUB360" title="688165-4: FILTRO DE LINEA BUB360" /><area shape="rect" coords="448,1577,490,1610" href="#688165-4" alt="688165-4: FILTRO DE LINEA BUB360" title="688165-4: FILTRO DE LINEA BUB360" /><area shape="rect" coords="353,1634,391,1668" href="#688165-4" alt="688165-4: FILTRO DE LINEA BUB360" title="688165-4: FILTRO DE LINEA BUB360" /><area shape="rect" coords="432,1280,1495,2203" href="#454662-0" alt="454662-0: DECK" title="454662-0: DECK" /><area shape="rect" coords="941,2162,1335,2360" href="#453239-8" alt="453239-8: TAPA INFERIOR LM430D" title="453239-8: TAPA INFERIOR LM430D" /><area shape="rect" coords="1215,2372,1226,2400" href="#266326-2" alt="266326-2: TORNILLO M4X18" title="266326-2: TORNILLO M4X18" /><area shape="rect" coords="238,2200,298,2239" href="#224444-2" alt="224444-2: ARANDELA INTERIOR LM430D" title="224444-2: ARANDELA INTERIOR LM430D" /><area shape="rect" coords="20,2128,516,2449" href="#196060-9" alt="196060-9: CUCHILLA LM430D" title="196060-9: CUCHILLA LM430D" /><area shape="rect" coords="238,2363,298,2401" href="#224445-0" alt="224445-0: ARANDELA EXTERIOR LM430D" title="224445-0: ARANDELA EXTERIOR LM430D" /><area shape="rect" coords="252,2427,284,2480" href="#266731-3" alt="266731-3: TORNILLO CUCHILLA  LM430D" title="266731-3: TORNILLO CUCHILLA  LM430D" /><area shape="rect" coords="1601,1420,1644,1451" href="#921352-5" alt="921352-5: TORNILLO ASA ALTURA LM430D" title="921352-5: TORNILLO ASA ALTURA LM430D" /><area shape="rect" coords="1566,1398,1597,1423" href="#257670-8" alt="257670-8: CASQUILLO PALANCA LM430D" title="257670-8: CASQUILLO PALANCA LM430D" /><area shape="rect" coords="1337,1198,1557,1390" href="#453255-0" alt="453255-0: PLACA REGULACION LM430D" title="453255-0: PLACA REGULACION LM430D" /><area shape="rect" coords="1323,1320,1335,1348" href="#266326-2" alt="266326-2: TORNILLO M4X18" title="266326-2: TORNILLO M4X18" /><area shape="rect" coords="1335,1265,1352,1282" href="#931302-2" alt="931302-2: TUERCA HEXAGONAL M6*" title="931302-2: TUERCA HEXAGONAL M6*" /><area shape="rect" coords="1315,1171,1342,1190" href="#266326-2" alt="266326-2: TORNILLO M4X18" title="266326-2: TORNILLO M4X18" /><area shape="rect" coords="1344,1185,1360,1206" href="#267102-7" alt="267102-7: ARANDELA 4 LM430D" title="267102-7: ARANDELA 4 LM430D" /><area shape="rect" coords="1359,1195,1384,1217" href="#231297-2" alt="231297-2: MUELLE 9" title="231297-2: MUELLE 9" /><area shape="rect" coords="1382,1202,1413,1241" href="#253808-3" alt="253808-3: ARANDELA 9 LM430D" title="253808-3: ARANDELA 9 LM430D" /><area shape="rect" coords="1535,1133,1674,1413" href="#453252-6" alt="453252-6: PALANCA ALTURA LM430D" title="453252-6: PALANCA ALTURA LM430D" /><area shape="rect" coords="1646,1161,1723,1277" href="#453253-4" alt="453253-4: TAPA PALANCA ALTURA LM430D" title="453253-4: TAPA PALANCA ALTURA LM430D" /><area shape="rect" coords="428,941,454,960" href="#266326-2" alt="266326-2: TORNILLO M4X18" title="266326-2: TORNILLO M4X18" /></map><map name="LM430DWBE_1"><area shape="rect" coords="331,380,504,602" href="#453241-1" alt="453241-1: TAPACUBOS RUEDA TRASERA LM430D" title="453241-1: TAPACUBOS RUEDA TRASERA LM430D" /><area shape="rect" coords="491,533,519,562" href="#252145-2" alt="252145-2: TUERCA HEXAGONAL M8 PS220TH" title="252145-2: TUERCA HEXAGONAL M8 PS220TH" /><area shape="rect" coords="526,553,552,578" href="#214067-4" alt="214067-4: RODAMIENTO RUEDA LM430D" title="214067-4: RODAMIENTO RUEDA LM430D" /><area shape="rect" coords="533,501,748,746" href="#453243-7" alt="453243-7: RUEDA TRASERA LM430D" title="453243-7: RUEDA TRASERA LM430D" /><area shape="rect" coords="737,667,781,718" href="#210070-3" alt="210070-3: RODAMIENTO BOLAS 6200ZZ MT240" title="210070-3: RODAMIENTO BOLAS 6200ZZ MT240" /><area shape="rect" coords="788,705,1287,986" href="#165669-8" alt="165669-8: EJE RUEDA TRASERA LM430D" title="165669-8: EJE RUEDA TRASERA LM430D" /><area shape="rect" coords="1268,973,1312,1024" href="#210070-3" alt="210070-3: RODAMIENTO BOLAS 6200ZZ MT240" title="210070-3: RODAMIENTO BOLAS 6200ZZ MT240" /><area shape="rect" coords="1306,947,1521,1192" href="#453243-7" alt="453243-7: RUEDA TRASERA LM430D" title="453243-7: RUEDA TRASERA LM430D" /><area shape="rect" coords="1512,1121,1537,1147" href="#214067-4" alt="214067-4: RODAMIENTO RUEDA LM430D" title="214067-4: RODAMIENTO RUEDA LM430D" /><area shape="rect" coords="1547,1138,1575,1168" href="#252145-2" alt="252145-2: TUERCA HEXAGONAL M8 PS220TH" title="252145-2: TUERCA HEXAGONAL M8 PS220TH" /><area shape="rect" coords="1588,1114,1759,1333" href="#453241-1" alt="453241-1: TAPACUBOS RUEDA TRASERA LM430D" title="453241-1: TAPACUBOS RUEDA TRASERA LM430D" /><area shape="rect" coords="899,850,911,878" href="#266326-2" alt="266326-2: TORNILLO M4X18" title="266326-2: TORNILLO M4X18" /><area shape="rect" coords="894,812,936,839" href="#346545-7" alt="346545-7: PLACA EJE LM430D" title="346545-7: PLACA EJE LM430D" /><area shape="rect" coords="1576,1486,1594,1504" href="#252103-8" alt="252103-8: TUERCA M5-8*" title="252103-8: TUERCA M5-8*" /><area shape="rect" coords="1551,1470,1566,1489" href="#941101-4" alt="941101-4: ARANDELA PLANA 5*" title="941101-4: ARANDELA PLANA 5*" /><area shape="rect" coords="886,1410,1537,1839" href="#346543-1" alt="346543-1: VARILLA UNION RUEDAS LM430D" title="346543-1: VARILLA UNION RUEDAS LM430D" /><area shape="rect" coords="1080,1586,1324,1783" href="#231875-8" alt="231875-8: MUELLE TENSION 16 LM430D" title="231875-8: MUELLE TENSION 16 LM430D" /><area shape="rect" coords="920,1838,935,1857" href="#941101-4" alt="941101-4: ARANDELA PLANA 5*" title="941101-4: ARANDELA PLANA 5*" /><area shape="rect" coords="944,1853,962,1871" href="#252103-8" alt="252103-8: TUERCA M5-8*" title="252103-8: TUERCA M5-8*" /><area shape="rect" coords="1099,2006,1242,2190" href="#453240-3" alt="453240-3: TAPACUBOS RUEDA DELANTE LM430D" title="453240-3: TAPACUBOS RUEDA DELANTE LM430D" /><area shape="rect" coords="1079,2034,1107,2063" href="#252145-2" alt="252145-2: TUERCA HEXAGONAL M8 PS220TH" title="252145-2: TUERCA HEXAGONAL M8 PS220TH" /><area shape="rect" coords="1057,2023,1082,2049" href="#214067-4" alt="214067-4: RODAMIENTO RUEDA LM430D" title="214067-4: RODAMIENTO RUEDA LM430D" /><area shape="rect" coords="892,1883,1079,2093" href="#453242-9" alt="453242-9: RUEDA DELANTERA LM430D" title="453242-9: RUEDA DELANTERA LM430D" /><area shape="rect" coords="852,1898,896,1949" href="#210070-3" alt="210070-3: RODAMIENTO BOLAS 6200ZZ MT240" title="210070-3: RODAMIENTO BOLAS 6200ZZ MT240" /><area shape="rect" coords="399,1646,874,1910" href="#165668-0" alt="165668-0: EJE RUEDA DELANT. LM430D" title="165668-0: EJE RUEDA DELANT. LM430D" /><area shape="rect" coords="515,1798,527,1827" href="#266326-2" alt="266326-2: TORNILLO M4X18" title="266326-2: TORNILLO M4X18" /><area shape="rect" coords="511,1755,561,1787" href="#341462-6" alt="341462-6: PLETINA PARA JR3000V" title="341462-6: PLETINA PARA JR3000V" /><area shape="rect" coords="354,1611,398,1662" href="#210070-3" alt="210070-3: RODAMIENTO BOLAS 6200ZZ MT240" title="210070-3: RODAMIENTO BOLAS 6200ZZ MT240" /><area shape="rect" coords="182,1473,369,1683" href="#453242-9" alt="453242-9: RUEDA DELANTERA LM430D" title="453242-9: RUEDA DELANTERA LM430D" /><area shape="rect" coords="171,1512,196,1537" href="#214067-4" alt="214067-4: RODAMIENTO RUEDA LM430D" title="214067-4: RODAMIENTO RUEDA LM430D" /><area shape="rect" coords="137,1493,165,1523" href="#252145-2" alt="252145-2: TUERCA HEXAGONAL M8 PS220TH" title="252145-2: TUERCA HEXAGONAL M8 PS220TH" /><area shape="rect" coords="6,1369,151,1554" href="#453240-3" alt="453240-3: TAPACUBOS RUEDA DELANTE LM430D" title="453240-3: TAPACUBOS RUEDA DELANTE LM430D" /></map><map name="LM430DWBE_2"><area shape="rect" coords="1068,29,1572,451" href="#331975-5" alt="331975-5: PALANCA INTERRUPTOR LM430D" title="331975-5: PALANCA INTERRUPTOR LM430D" /><area shape="rect" coords="1479,479,1551,560" href="#453246-1" alt="453246-1: CAJA PALANCA INTERRUP. LM430D" title="453246-1: CAJA PALANCA INTERRUP. LM430D" /><area shape="rect" coords="1415,439,1492,527" href="#453247-9" alt="453247-9: TAPA PALANCA INTERRUP. LM430D" title="453247-9: TAPA PALANCA INTERRUP. LM430D" /><area shape="rect" coords="1385,442,1411,461" href="#266326-2" alt="266326-2: TORNILLO M4X18" title="266326-2: TORNILLO M4X18" /><area shape="rect" coords="1240,304,1266,323" href="#266326-2" alt="266326-2: TORNILLO M4X18" title="266326-2: TORNILLO M4X18" /><area shape="rect" coords="1049,240,1212,443" href="#141298-1" alt="141298-1: CAJA INTERRUP. LM430D" title="141298-1: CAJA INTERRUP. LM430D" /><area shape="rect" coords="1079,219,1107,239" href="#911138-5" alt="911138-5: TORNILLO M4X20*" title="911138-5: TORNILLO M4X20*" /><area shape="rect" coords="1002,191,1078,299" href="#453248-7" alt="453248-7: PALANCA LM430D" title="453248-7: PALANCA LM430D" /><area shape="rect" coords="1000,196,1041,216" href="#231876-6" alt="231876-6: MUELLE PALANCA LM430D" title="231876-6: MUELLE PALANCA LM430D" /><area shape="rect" coords="917,176,991,258" href="#453249-5" alt="453249-5: BOTON INTERRUP. LM430D" title="453249-5: BOTON INTERRUP. LM430D" /><area shape="rect" coords="899,170,929,192" href="#233068-3" alt="233068-3: MUELLE PALANCA 6 LM430D" title="233068-3: MUELLE PALANCA 6 LM430D" /><area shape="rect" coords="863,204,909,255" href="#650681-6" alt="650681-6: INTERRUPTOR. LM430D" title="650681-6: INTERRUPTOR. LM430D" /><area shape="rect" coords="741,63,910,271" href="#453244-5" alt="453244-5: CAJA INTERRUP. LM430D" title="453244-5: CAJA INTERRUP. LM430D" /><area shape="rect" coords="945,314,975,344" href="#687123-7" alt="687123-7: PRESILLA P/MT601" title="687123-7: PRESILLA P/MT601" /><area shape="rect" coords="983,339,1010,358" href="#266326-2" alt="266326-2: TORNILLO M4X18" title="266326-2: TORNILLO M4X18" /><area shape="rect" coords="590,473,1500,1464" href="#141299-9" alt="141299-9: MANILLAR SUPERIOR LM430D" title="141299-9: MANILLAR SUPERIOR LM430D" /><area shape="rect" coords="322,285,917,1354" href="#664780-8" alt="664780-8: CABLE LM430D" title="664780-8: CABLE LM430D" /><area shape="rect" coords="576,1015,640,1060" href="#266730-5" alt="266730-5: TORNILLO 6X50 LM430D" title="266730-5: TORNILLO 6X50 LM430D" /><area shape="rect" coords="723,1081,807,1178" href="#264070-5" alt="264070-5: POMO TORNILLO M6 LM430D" title="264070-5: POMO TORNILLO M6 LM430D" /><area shape="rect" coords="987,1233,1071,1331" href="#264070-5" alt="264070-5: POMO TORNILLO M6 LM430D" title="264070-5: POMO TORNILLO M6 LM430D" /><area shape="rect" coords="1151,1350,1215,1395" href="#266730-5" alt="266730-5: TORNILLO 6X50 LM430D" title="266730-5: TORNILLO 6X50 LM430D" /><area shape="rect" coords="177,1351,1189,2434" href="#331973-9" alt="331973-9: MANILLAR INFERIOR LM430D" title="331973-9: MANILLAR INFERIOR LM430D" /><area shape="rect" coords="426,1637,478,1682" href="#453385-7" alt="453385-7: PINZA CABLE LM430D" title="453385-7: PINZA CABLE LM430D" /><area shape="rect" coords="66,2028,172,2150" href="#266729-0" alt="266729-0: POMO MANILLAR M8 LM430D" title="266729-0: POMO MANILLAR M8 LM430D" /><area shape="rect" coords="670,2372,777,2495" href="#266729-0" alt="266729-0: POMO MANILLAR M8 LM430D" title="266729-0: POMO MANILLAR M8 LM430D" /></map><map name="LM430DWBE_3"><area shape="rect" coords="716,716,1534,1662" href="#142245-5" alt="142245-5: REAR BAG COMPLETE" title="142245-5: REAR BAG COMPLETE" /><area shape="rect" coords="226,1321,656,1868" href="#326118-2" alt="326118-2: VARILLA RECOGEDOR CPL.LM430D" title="326118-2: VARILLA RECOGEDOR CPL.LM430D" /><area shape="rect" coords="575,1597,609,1627" href="#267438-4" alt="267438-4: FLAT WASHER 5" title="267438-4: FLAT WASHER 5" /><area shape="rect" coords="600,1635,616,1660" href="#266326-2" alt="266326-2: TORNILLO M4X18" title="266326-2: TORNILLO M4X18" /></map>